topsis/__init__.py
topsis/topsis.py
topsis_ishika_102303460-1.0.0.dist-info/METADATA
topsis_ishika_102303460-1.0.0.dist-info/WHEEL
topsis_ishika_102303460-1.0.0.dist-info/entry_points.txt
topsis_ishika_102303460-1.0.0.dist-info/top_level.txt
topsis_ishika_102303460-1.0.0.dist-info/RECORD
