Metadata-Version: 2.4
Name: Topsis-Ishika-102303460
Version: 1.0.0
Summary: TOPSIS implementation using Python
Author: Ishika
Requires-Dist: pandas
Requires-Dist: numpy
Dynamic: author
Dynamic: description
Dynamic: description-content-type
Dynamic: requires-dist
Dynamic: summary
